ip_searcher/__init__.py
ip_searcher/xdbSearcher.py
ip_searcher-2024.5.27.11.46.42.dist-info/LICENSE
ip_searcher-2024.5.27.11.46.42.dist-info/LICENSE.md
ip_searcher-2024.5.27.11.46.42.dist-info/METADATA
ip_searcher-2024.5.27.11.46.42.dist-info/WHEEL
ip_searcher-2024.5.27.11.46.42.dist-info/entry_points.txt
ip_searcher-2024.5.27.11.46.42.dist-info/top_level.txt
ip_searcher-2024.5.27.11.46.42.dist-info/RECORD
