Metadata-Version: 2.1
Name: ip_searcher
Version: 2024.5.27.11.46.42
Summary: description
Home-page: https://github.com/yuanjie-ai/ip_searcher
Author: yuanjie
Author-email: 313303303@qq.com
Maintainer: yuanjie
Maintainer-email: 313303303@qq.com
License: MIT License
Keywords: utils
Platform: all
Classifier: Operating System :: OS Independent
Classifier: Intended Audience :: Developers
Classifier: License :: OSI Approved :: MIT License
Classifier: Programming Language :: Python
Classifier: Programming Language :: Python :: Implementation
Requires-Python: >=3.6
License-File: LICENSE
License-File: LICENSE.md
Requires-Dist: meutils
Provides-Extra: all
